aptamerutils/__init__.py
aptamerutils/_dist.py
aptamerutils/_distmap.py
aptamerutils/_posmap.py
aptamerutils/_textrenderer.py
aptamerutils/find.py
aptamerutils/seqlist.py
aptamerutils/sequence.py
aptamerutils-0.3.0.dist-info/licenses/LICENSE
aptamerutils-0.3.0.dist-info/METADATA
aptamerutils-0.3.0.dist-info/WHEEL
aptamerutils-0.3.0.dist-info/top_level.txt
aptamerutils-0.3.0.dist-info/RECORD
