Metadata-Version: 2.4
Name: aptamerutils
Version: 0.3.0
Summary: Aptamer sequence analysis utilities
Author-email: creeper349 <1601789895@qq.com>
License: MIT
Project-URL: Repository, https://github.com/creeper349/aptamerutils
Requires-Python: >=3.10
License-File: LICENSE
Requires-Dist: numpy
Requires-Dist: scikit-learn
Requires-Dist: matplotlib
Requires-Dist: umap-learn
Requires-Dist: viennarna
Requires-Dist: hdbscan
Requires-Dist: regex
Dynamic: license-file
